polish_parliament/__init__.py
polish_parliament/api/__init__.py
polish_parliament/api/default/__init__.py
polish_parliament/api/default/get_sejm_term.py
polish_parliament/api/default/get_sejm_termterm.py
polish_parliament/api/default/get_sejm_termterm_clubs.py
polish_parliament/api/default/get_sejm_termterm_clubs_id.py
polish_parliament/api/default/get_sejm_termterm_clubs_id_logo.py
polish_parliament/api/default/get_sejm_termterm_committees.py
polish_parliament/api/default/get_sejm_termterm_committees_code.py
polish_parliament/api/default/get_sejm_termterm_interpellations.py
polish_parliament/api/default/get_sejm_termterm_interpellations_num.py
polish_parliament/api/default/get_sejm_termterm_interpellations_num_body.py
polish_parliament/api/default/get_sejm_termterm_interpellations_num_reply_key_body.py
polish_parliament/api/default/get_sejm_termterm_mp.py
polish_parliament/api/default/get_sejm_termterm_mp_id.py
polish_parliament/api/default/get_sejm_termterm_mp_id_photo.py
polish_parliament/api/default/get_sejm_termterm_mp_id_photo_mini.py
polish_parliament/api/default/get_sejm_termterm_prints.py
polish_parliament/api/default/get_sejm_termterm_prints_num.py
polish_parliament/api/default/get_sejm_termterm_prints_num_attach_name.py
polish_parliament/api/default/get_sejm_termterm_proceedings.py
polish_parliament/api/default/get_sejm_termterm_proceedings_id.py
polish_parliament/api/default/get_sejm_termterm_processes.py
polish_parliament/api/default/get_sejm_termterm_processes_num.py
polish_parliament/api/default/get_sejm_termterm_videos.py
polish_parliament/api/default/get_sejm_termterm_videos_today.py
polish_parliament/api/default/get_sejm_termterm_votings_sitting.py
polish_parliament/api/default/get_sejm_termterm_written_questions.py
polish_parliament/api/default/get_sejm_termterm_written_questions_num.py
polish_parliament/api/default/get_sejm_termterm_written_questions_num_body.py
polish_parliament-1.0.dist-info/LICENSE
polish_parliament-1.0.dist-info/METADATA
polish_parliament-1.0.dist-info/WHEEL
polish_parliament-1.0.dist-info/RECORD
